dupliCat/__init__.py
dupliCat/__main__.py
dupliCat-3.7.2.dist-info/LICENSE
dupliCat-3.7.2.dist-info/METADATA
dupliCat-3.7.2.dist-info/WHEEL
dupliCat-3.7.2.dist-info/entry_points.txt
dupliCat-3.7.2.dist-info/top_level.txt
dupliCat-3.7.2.dist-info/RECORD
