Metadata-Version: 2.1
Name: dupliCat
Version: 3.7.2
Summary: A simple package to hunt down file duplicates.
Home-page: https://github.com/teddbug-S/dupliCat
Author: Divine Darkey (teddbug-S)
Author-email: teddbug47@gmail.com
Maintainer: Divine Darkey (teddbug-S)
Maintainer-email: teddbug47@gmail.com
License: MIT
Project-URL: Issues, https://github.com/teddbug-S/dupliCat/issues
Project-URL: Pull Requests, https://github.com/teddbug-S/dupliCat/pulls
Classifier: Programming Language :: Python :: 3
Classifier: License :: OSI Approved :: MIT License
Classifier: Operating System :: OS Independent
Classifier: Development Status :: 5 - Production/Stable
Classifier: Intended Audience :: Developers
Requires: click
Requires-Python: >=3.6
License-File: LICENSE
